rpios_tools/__init__.py
rpios_tools/customize.py
rpios_tools/docker.py
rpios_tools/download.py
rpios_tools/image.py
rpios_tools/utils.py
rpios_tools/docker/Dockerfile
rpios_tools/docker/entrypoint.sh
rpios_tools/docker/requirements.txt
rpios_tools/scripts/install_osxfuse_2.sh
rpios_tools-0.3.0.dist-info/LICENSE
rpios_tools-0.3.0.dist-info/METADATA
rpios_tools-0.3.0.dist-info/WHEEL
rpios_tools-0.3.0.dist-info/entry_points.txt
rpios_tools-0.3.0.dist-info/top_level.txt
rpios_tools-0.3.0.dist-info/RECORD
