Metadata-Version: 2.1
Name: rpios-tools
Version: 0.3.0
Summary: Automated tools for working with raspberry pi image development
Home-page: https://github.com/michael-sobczak/rpi-os-tools
Author: Michael Sobczak
Author-email: 86268116+michael-sobczak@users.noreply.github.com
License: MIT
Keywords: raspberry pi,raspbian,iot,rpi
Platform: UNKNOWN
Classifier: Intended Audience :: Developers
Classifier: License :: OSI Approved :: MIT License
Classifier: Operating System :: OS Independent
Classifier: Programming Language :: Python
Classifier: Topic :: Software Development :: Libraries :: Python Modules
Requires-Dist: attrs (==21.2.0)
Requires-Dist: beautifulsoup4 (==4.9.3)
Requires-Dist: bleach (==3.3.0)
Requires-Dist: certifi (==2021.5.30)
Requires-Dist: chardet (==4.0.0)
Requires-Dist: colorama (==0.4.4)
Requires-Dist: docutils (==0.17.1)
Requires-Dist: idna (==2.10)
Requires-Dist: importlib-metadata (==4.5.0)
Requires-Dist: iniconfig (==1.1.1)
Requires-Dist: keyring (==23.0.1)
Requires-Dist: packaging (==20.9)
Requires-Dist: pkginfo (==1.7.0)
Requires-Dist: pluggy (==0.13.1)
Requires-Dist: psutil (==5.8.0)
Requires-Dist: py (==1.10.0)
Requires-Dist: Pygments (==2.9.0)
Requires-Dist: pyparsing (==2.4.7)
Requires-Dist: readme-renderer (==29.0)
Requires-Dist: requests (==2.25.1)
Requires-Dist: requests-toolbelt (==0.9.1)
Requires-Dist: rfc3986 (==1.5.0)
Requires-Dist: six (==1.16.0)
Requires-Dist: soupsieve (==2.2.1)
Requires-Dist: toml (==0.10.2)
Requires-Dist: tqdm (==4.61.1)
Requires-Dist: twine (==3.4.1)
Requires-Dist: urllib3 (==1.26.5)
Requires-Dist: webencodings (==0.5.1)
Requires-Dist: zipp (==3.4.1)
